imagej_rolling_ball/__init__.py
imagej_rolling_ball/bg_subtracter.py
imagej_rolling_ball/cli/__init__.py
imagej_rolling_ball/cli/rolling_ball.py
imagej_rolling_ball-2024.6.1.dist-info/LICENSE
imagej_rolling_ball-2024.6.1.dist-info/METADATA
imagej_rolling_ball-2024.6.1.dist-info/WHEEL
imagej_rolling_ball-2024.6.1.dist-info/entry_points.txt
imagej_rolling_ball-2024.6.1.dist-info/RECORD
