Metadata-Version: 2.1
Name: imagej-rolling-ball
Version: 2024.6.1
Summary: Python wrapper for ImageJ's rolling ball background subtraction using pyimagej
Home-page: https://pypi.org/project/imagej-rolling-ball
Keywords: microscopy,imagej,background subtraction,image processing
Author: Yu-An Chen
Author-email: atwood12@gmail.com
Requires-Python: >=3.8,<4.0
Classifier: Programming Language :: Python :: 3
Classifier: Programming Language :: Python :: 3.8
Classifier: Programming Language :: Python :: 3.9
Classifier: Programming Language :: Python :: 3.10
Classifier: Programming Language :: Python :: 3.11
Provides-Extra: large
Provides-Extra: wsi
Requires-Dist: dask (>=2021.10.0) ; extra == "large"
Requires-Dist: fire (>=0.5.0) ; extra == "wsi"
Requires-Dist: palom (>=2023.8.1) ; extra == "wsi"
Requires-Dist: pyimagej (>=1.4.1,<1.5.0)
Requires-Dist: zarr (>=2.10,<2.15) ; extra == "large"
Project-URL: Repository, https://github.com/Yu-AnChen/imagej-rolling-ball
